[{"name": "benchmarks.TimeCreation.time_create_from_tuple", "idx": null, "pretty_name": "benchmarks.TimeCreation.time_create_from_tuple", "last_rev": 1148, "last_value": 0.025472925000030955, "last_err": 0.0003066016200292125, "prev_value": 0.047490736502368236, "change_rev": [null, 1086]}, {"name": "benchmarks.TimeCreation.time_create_single", "idx": null, "pretty_name": "benchmarks.TimeCreation.time_create_single", "last_rev": 1148, "last_value": 0.03962191999744391, "last_err": 0.0004950461355140053, "prev_value": 0.025748813004611293, "change_rev": [1099, 1101]}, {"name": "benchmarks.TimeScalarInterval.time_abs", "idx": null, "pretty_name": "benchmarks.TimeScalarInterval.time_abs", "last_rev": 1148, "last_value": 0.0025206713999978096, "last_err": 1.8200142844631745e-05, "prev_value": 0.002137951499935298, "change_rev": [1099, 1101]}, {"name": "benchmarks.TimeScalarInterval.time_add", "idx": null, "pretty_name": "benchmarks.TimeScalarInterval.time_add", "last_rev": 1148, "last_value": 0.0026288925000130803, "last_err": 3.374133380171404e-05, "prev_value": 0.0025358958746437565, "change_rev": [1130, 1134]}, {"name": "benchmarks.TimeScalarInterval.time_bool", "idx": null, "pretty_name": "benchmarks.TimeScalarInterval.time_bool", "last_rev": 1148, "last_value": 2.5242441179751253e-05, "last_err": 3.173487298374935e-07, "prev_value": 1.7510275042494253e-05, "change_rev": [null, 1082]}, {"name": "benchmarks.TimeScalarInterval.time_inplace_add", "idx": null, "pretty_name": "benchmarks.TimeScalarInterval.time_inplace_add", "last_rev": 1148, "last_value": 0.002477873299994826, "last_err": 1.8930755376590637e-05, "prev_value": 0.0014236249375016996, "change_rev": [1099, 1101]}, {"name": "benchmarks.TimeScalarInterval.time_inplace_mul", "idx": null, "pretty_name": "benchmarks.TimeScalarInterval.time_inplace_mul", "last_rev": 1148, "last_value": 0.003087010874992302, "last_err": 1.4175395657876197e-05, "prev_value": 0.0024028053005167747, "change_rev": [null, 1138]}, {"name": "benchmarks.TimeScalarInterval.time_mid_rad", "idx": null, "pretty_name": "benchmarks.TimeScalarInterval.time_mid_rad", "last_rev": 1148, "last_value": 4.361435019944677e-05, "last_err": 2.43879810543899e-07, "prev_value": 2.5199073634493096e-05, "change_rev": [null, 1140]}, {"name": "benchmarks.TimeScalarInterval.time_mul_mixed", "idx": null, "pretty_name": "benchmarks.TimeScalarInterval.time_mul_mixed", "last_rev": 1148, "last_value": 0.0026845700003832462, "last_err": 3.35936131693291e-05, "prev_value": 0.004859615331952227, "change_rev": [null, 1086]}, {"name": "benchmarks.TimeScalarInterval.time_mul_negative", "idx": null, "pretty_name": "benchmarks.TimeScalarInterval.time_mul_negative", "last_rev": 1148, "last_value": 0.0025923827497535967, "last_err": 2.3350665067228813e-05, "prev_value": 0.0026529742499405984, "change_rev": [null, 1092]}, {"name": "benchmarks.TimeScalarInterval.time_mul_positive", "idx": null, "pretty_name": "benchmarks.TimeScalarInterval.time_mul_positive", "last_rev": 1148, "last_value": 0.0032810370003062417, "last_err": 4.255574888578914e-05, "prev_value": 0.0025832299998000963, "change_rev": [null, 1139]}, {"name": "benchmarks.TimeScalarInterval.time_neg", "idx": null, "pretty_name": "benchmarks.TimeScalarInterval.time_neg", "last_rev": 1148, "last_value": 0.002505872374968021, "last_err": 2.5119241762456976e-05, "prev_value": 0.004670077666560246, "change_rev": [null, 1086]}, {"name": "benchmarks.TimeScalarInterval.time_sub", "idx": null, "pretty_name": "benchmarks.TimeScalarInterval.time_sub", "last_rev": 1148, "last_value": 0.002532992125452438, "last_err": 1.5678920332138642e-05, "prev_value": 0.0025527008756398573, "change_rev": [1099, 1101]}, {"name": "benchmarks.TimeScalarInterval.time_truediv", "idx": null, "pretty_name": "benchmarks.TimeScalarInterval.time_truediv", "last_rev": 1148, "last_value": 0.006444236500101397, "last_err": 6.407088689790855e-05, "prev_value": 0.004764422666388176, "change_rev": [1099, 1101]}, {"name": "benchmarks.TimeScalarIntervalLarge.time_add_large", "idx": 0, "pretty_name": "benchmarks.TimeScalarIntervalLarge.time_add_large(1000)", "last_rev": 1148, "last_value": 0.02550109249568777, "last_err": 0.00026818533691482167, "prev_value": 0.0474941115026013, "change_rev": [null, 1086]}, {"name": "benchmarks.TimeScalarIntervalLarge.time_add_large", "idx": 1, "pretty_name": "benchmarks.TimeScalarIntervalLarge.time_add_large(10000)", "last_rev": 1148, "last_value": 0.25517570349984453, "last_err": 0.002311064156478424, "prev_value": 0.4730598180030938, "change_rev": [null, 1086]}, {"name": "benchmarks.TimeScalarIntervalLarge.time_add_large", "idx": 2, "pretty_name": "benchmarks.TimeScalarIntervalLarge.time_add_large(100000)", "last_rev": 1148, "last_value": 2.6494345285000236, "last_err": 0.02741170809348145, "prev_value": 2.5587713869972504, "change_rev": [1130, 1134]}, {"name": "benchmarks.TimeScalarIntervalLarge.time_mul_large", "idx": 0, "pretty_name": "benchmarks.TimeScalarIntervalLarge.time_mul_large(1000)", "last_rev": 1148, "last_value": 0.025974758998927427, "last_err": 0.00038163774369705337, "prev_value": 0.048250568499497604, "change_rev": [null, 1086]}, {"name": "benchmarks.TimeScalarIntervalLarge.time_mul_large", "idx": 1, "pretty_name": "benchmarks.TimeScalarIntervalLarge.time_mul_large(10000)", "last_rev": 1148, "last_value": 0.25938709999536513, "last_err": 0.0026703416241635096, "prev_value": 0.26750059600090026, "change_rev": [null, 1092]}, {"name": "benchmarks.TimeScalarIntervalLarge.time_mul_large", "idx": 2, "pretty_name": "benchmarks.TimeScalarIntervalLarge.time_mul_large(100000)", "last_rev": 1148, "last_value": 2.599196352501167, "last_err": 0.024782123932541478, "prev_value": 2.658500981498946, "change_rev": [null, 1092]}]